{"web":{"client_id":"164586149788-4lm7boi6k4e6989ravv153ambhfesoui.apps.googleusercontent.com","project_id":"satyam01","auth_uri":"https://accounts.google.com/o/oauth2/auth","token_uri":"https://oauth2.googleapis.com/token","auth_provider_x509_cert_url":"https://www.googleapis.com/oauth2/v1/certs","client_secret":"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","redirect_uris":["http://localhost:8000/api/v1/auth/facebook/callback","http://localhost:4000/instagramData/api/v1/auth/google/","http://localhost:8000/api/v1/auth/google/callback","http://localhost:8000/api/v1/auth/google","http://localhost:8000/","http://localhost:8501/"],"javascript_origins":["http://localhost:4000","http://localhost:8000","http://localhost:8501"]}}